Metadata-Version: 2.1
Name: calculator-package-foxylex
Version: 1.0.0
Summary: A simple calculator package
Home-page: https://github.com/foxylex/calculator_package_foxylex
Author: Laura Aleksiune
Author-email: lau.kanapienyte@gmail.com
License: MIT
Classifier: License :: OSI Approved :: MIT License
Classifier: Programming Language :: Python :: 3
Classifier: Programming Language :: Python :: 3.9
Requires-Python: >=3.6
License-File: LICENSE.txt
